talkabout/__init__.py
talkabout/main.py
talkabout-0.1.3.dist-info/licenses/LICENSE
talkabout-0.1.3.dist-info/METADATA
talkabout-0.1.3.dist-info/WHEEL
talkabout-0.1.3.dist-info/top_level.txt
talkabout-0.1.3.dist-info/RECORD
