Metadata-Version: 2.4
Name: talkabout
Version: 0.1.3
Summary: AI-powered object query proxy using Claude AI
Home-page: https://github.com/babochenko/talkabout
Author: Denis Babochenko
Author-email: Denis Babochenko <babochenko.denis2@gmail.com>
Project-URL: Homepage, https://github.com/babochenko/talkabout
Project-URL: Repository, https://github.com/babochenko/talkabout
Project-URL: Issues, https://github.com/babochenko/talkabout/issues
Classifier: Development Status :: 3 - Alpha
Classifier: Intended Audience :: Developers
Classifier: License :: OSI Approved :: MIT License
Classifier: Operating System :: OS Independent
Classifier: Programming Language :: Python :: 3
Classifier: Programming Language :: Python :: 3.8
Classifier: Programming Language :: Python :: 3.9
Classifier: Programming Language :: Python :: 3.10
Classifier: Programming Language :: Python :: 3.11
Classifier: Programming Language :: Python :: 3.12
Classifier: Topic :: Software Development :: Libraries :: Python Modules
Classifier: Topic :: Scientific/Engineering :: Artificial Intelligence
Requires-Python: >=3.8
License-File: LICENSE
Requires-Dist: anthropic>=0.18.0
Provides-Extra: dev
Requires-Dist: pytest>=6.0; extra == "dev"
Requires-Dist: black>=22.0; extra == "dev"
Requires-Dist: flake8>=4.0; extra == "dev"
Requires-Dist: mypy>=0.900; extra == "dev"
Dynamic: author
Dynamic: home-page
Dynamic: license-file
Dynamic: requires-python
